wis/__init__.py
wis/kernels.py
wis/satellite_obscodes.py
wis/wis.py
wis-1.0.0.dist-info/AUTHORS.rst
wis-1.0.0.dist-info/LICENSE
wis-1.0.0.dist-info/METADATA
wis-1.0.0.dist-info/WHEEL
wis-1.0.0.dist-info/top_level.txt
wis-1.0.0.dist-info/RECORD
