Metadata-Version: 2.1
Name: wis
Version: 1.0.0
Summary: wis.py gives satellite positions at requested times. It manages kernel downloads. It requires astropy and spicepy. 
Home-page: https://github.com/matthewjohnpayne/wis
Author: Matthew John Payne
Author-email: matthewjohnpayne@gmail.com
License: MIT license
Keywords: wis
Platform: UNKNOWN
Classifier: Development Status :: 2 - Pre-Alpha
Classifier: Intended Audience :: Developers
Classifier: License :: OSI Approved :: MIT License
Classifier: Natural Language :: English
Classifier: Programming Language :: Python :: 3.5
Requires-Dist: numpy
Requires-Dist: pytest
Requires-Dist: spiceypy
Requires-Dist: bs4
Requires-Dist: wget
Requires-Dist: astropy
Requires-Dist: requests
